jupyter_docx_bundler/__init__.py
jupyter_docx_bundler/converters.py
jupyter_docx_bundler/pandoc_filter.py
jupyter_docx_bundler/tests/__init__.py
jupyter_docx_bundler/tests/conftest.py
jupyter_docx_bundler/tests/test_bundler.py
jupyter_docx_bundler/tests/test_converters.py
jupyter_docx_bundler-0.4.0.dist-info/LICENSE
jupyter_docx_bundler-0.4.0.dist-info/METADATA
jupyter_docx_bundler-0.4.0.dist-info/WHEEL
jupyter_docx_bundler-0.4.0.dist-info/entry_points.txt
jupyter_docx_bundler-0.4.0.dist-info/top_level.txt
jupyter_docx_bundler-0.4.0.dist-info/RECORD
