Metadata-Version: 2.1
Name: jupyter-docx-bundler
Version: 0.4.0
Summary: Jupyter bundler extension to export notebook as a docx file
Author-email: Marco Rossi <developer@marco-rossi.com>
Project-URL: repository, https://github.com/m-rossi/jupyter-docx-bundler
Project-URL: Bug Tracker, https://github.com/m-rossi/jupyter-docx-bundler/issues
Project-URL: changelog, https://github.com/m-rossi/jupyter-docx-bundler/blob/main/CHANGELOG.md
Classifier: Development Status :: 4 - Beta
Classifier: Framework :: Jupyter :: JupyterLab
Classifier: Framework :: Jupyter
Classifier: License :: OSI Approved :: MIT License
Classifier: Operating System :: OS Independent
Classifier: Programming Language :: Python :: 3
Classifier: Programming Language :: Python :: 3.8
Classifier: Programming Language :: Python :: 3.9
Classifier: Programming Language :: Python :: 3.10
Classifier: Programming Language :: Python :: 3.11
Requires-Python: >=3.6
License-File: LICENSE
Requires-Dist: lxml
Requires-Dist: nbconvert >=7.0
Requires-Dist: notebook >=7.0
Requires-Dist: pandas
Requires-Dist: pandocfilters
Requires-Dist: pypandoc >=1.4
Requires-Dist: requests
Requires-Dist: tabulate
Requires-Dist: importlib-resources ; python_version < "3.9"
Provides-Extra: test
Requires-Dist: ipython >=7.0 ; extra == 'test'
Requires-Dist: kaleido ; extra == 'test'
Requires-Dist: matplotlib >=3.1 ; extra == 'test'
Requires-Dist: mock ; extra == 'test'
Requires-Dist: nbformat ; extra == 'test'
Requires-Dist: numpy ; extra == 'test'
Requires-Dist: pillow >=6.0.0 ; extra == 'test'
Requires-Dist: plotly ; extra == 'test'
Requires-Dist: pytest ; extra == 'test'
Requires-Dist: pytest-cov ; extra == 'test'
Requires-Dist: pytest-lazy-fixture ; extra == 'test'
Requires-Dist: sympy ; extra == 'test'
